traffic.v
module traffic(CLR, T, CLK, GN, YN, RN, GE, YE, RE);

//Inputs
input CLK, CLR, T;
//Outputs
output GN, YN, RN, GE, YE, RE;
output reg J, K;
output reg [7:0] count;
//Clock Control
always @(posedge CLK)
begin
  if (CLR)begin
      J <= 0;
      K <= 0;
      count <= 0;
  end
    else begin
        if (count == 19)
        begin
            count <= 0;
            J <= (T & K) | (~T & J);
            K <= (T & K) | (~T & ~J);
        end
        else begin
            count <= count + 1;
        end
    end
end
 //Assignments
assign RN = J;
assign YN = ~J & K;
assign GN = ~J&~K;
assign RE = ~J;
assign YE = J&~K;
assign GE = J&K;
//End
endmodule

traffic_test.v
`include "traffic.v"
`timescale 10ns/10ns
module traffic_test;
//wire
 wire [7:0]count;
 //Input
 reg CLR;
  reg T = 1'b0;
  reg CLK = 1'b0;
  always 
  begin 
   CLK<=~CLK;
   #5;
  end
 //Clock
  always @(posedge CLK)begin
    if (count == 19)begin
      T = ~T; #10;
    end
  end
//Wires
 wire GN, YN, RN, GE, YE, RE;

  traffic UUT (CLR, T, CLK, GN, YN, RN, GE, YE, RE);
  initial begin
    $dumpfile("traffic.vcd");
    $dumpvars(0,traffic_test);
    $display("Start of test.");
    CLR <= 1'b1; #10;
    CLR <= 1'b0; #10;

    $display("T | GN YN RN | GE YE RE");
    for (integer i = 0; i < 11; i = i + 1)
    begin
      $display("%b |  %b  %b  %b  |  %b  %b  %b ", T, GN, YN, RN, GE, YE, RE); #200; T = ~T; 
    end
    $display("Test terminated."); 
    $finish;
end
endmodule

traffic.vcd
$date
	Mon Apr 19 00:04:22 2021
$end
$version
	Icarus Verilog
$end
$timescale
	10ns
$end
$scope module traffic_test $end
$var wire 8 ! count [7:0] $end
$var wire 1 " YN $end
$var wire 1 # YE $end
$var wire 1 $ RN $end
$var wire 1 % RE $end
$var wire 1 & GN $end
$var wire 1 ' GE $end
$var reg 1 ( CLK $end
$var reg 1 ) CLR $end
$var reg 1 * T $end
$scope module UUT $end
$var wire 1 ( CLK $end
$var wire 1 ) CLR $end
$var wire 1 ' GE $end
$var wire 1 & GN $end
$var wire 1 % RE $end
$var wire 1 $ RN $end
$var wire 1 * T $end
$var wire 1 # YE $end
$var wire 1 " YN $end
$var reg 1 + J $end
$var reg 1 , K $end
$var reg 8 - count [7:0] $end
$upscope $end
$scope begin $ivl_for_loop0 $end
$var integer 32 . i [31:0] $end
$upscope $end
$upscope $end
$enddefinitions $end
#0
$dumpvars
bx .
b0 -
0,
0+
0*
1)
1(
0'
1&
1%
0$
0#
0"
bz !
$end
#5
0(
#10
b1 -
1(
0)
#15
0(
#20
b10 -
1(
b0 .
#25
0(
#30
b11 -
1(
#35
0(
#40
b100 -
1(
#45
0(
#50
b101 -
1(
#55
0(
#60
b110 -
1(
#65
0(
#70
b111 -
1(
#75
0(
#80
b1000 -
1(
#85
0(
#90
b1001 -
1(
#95
0(
#100
b1010 -
1(
#105
0(
#110
b1011 -
1(
#115
0(
#120
b1100 -
1(
#125
0(
#130
b1101 -
1(
#135
0(
#140
b1110 -
1(
#145
0(
#150
b1111 -
1(
#155
0(
#160
b10000 -
1(
#165
0(
#170
b10001 -
1(
#175
0(
#180
b10010 -
1(
#185
0(
#190
b10011 -
1(
#195
0(
#200
0&
1"
1,
b0 -
1(
#205
0(
#210
b1 -
1(
#215
0(
#220
b10 -
1(
b1 .
1*
#225
0(
#230
b11 -
1(
#235
0(
#240
b100 -
1(
#245
0(
#250
b101 -
1(
#255
0(
#260
b110 -
1(
#265
0(
#270
b111 -
1(
#275
0(
#280
b1000 -
1(
#285
0(
#290
b1001 -
1(
#295
0(
#300
b1010 -
1(
#305
0(
#310
b1011 -
1(
#315
0(
#320
b1100 -
1(
#325
0(
#330
b1101 -
1(
#335
0(
#340
b1110 -
1(
#345
0(
#350
b1111 -
1(
#355
0(
#360
b10000 -
1(
#365
0(
#370
b10001 -
1(
#375
0(
#380
b10010 -
1(
#385
0(
#390
b10011 -
1(
#395
0(
#400
0"
1'
0%
1$
1+
b0 -
1(
#405
0(
#410
b1 -
1(
#415
0(
#420
b10 -
1(
b10 .
0*
#425
0(
#430
b11 -
1(
#435
0(
#440
b100 -
1(
#445
0(
#450
b101 -
1(
#455
0(
#460
b110 -
1(
#465
0(
#470
b111 -
1(
#475
0(
#480
b1000 -
1(
#485
0(
#490
b1001 -
1(
#495
0(
#500
b1010 -
1(
#505
0(
#510
b1011 -
1(
#515
0(
#520
b1100 -
1(
#525
0(
#530
b1101 -
1(
#535
0(
#540
b1110 -
1(
#545
0(
#550
b1111 -
1(
#555
0(
#560
b10000 -
1(
#565
0(
#570
b10001 -
1(
#575
0(
#580
b10010 -
1(
#585
0(
#590
b10011 -
1(
#595
0(
#600
1#
0'
0,
b0 -
1(
#605
0(
#610
b1 -
1(
#615
0(
#620
b10 -
1(
b11 .
1*
#625
0(
#630
b11 -
1(
#635
0(
#640
b100 -
1(
#645
0(
#650
b101 -
1(
#655
0(
#660
b110 -
1(
#665
0(
#670
b111 -
1(
#675
0(
#680
b1000 -
1(
#685
0(
#690
b1001 -
1(
#695
0(
#700
b1010 -
1(
#705
0(
#710
b1011 -
1(
#715
0(
#720
b1100 -
1(
#725
0(
#730
b1101 -
1(
#735
0(
#740
b1110 -
1(
#745
0(
#750
b1111 -
1(
#755
0(
#760
b10000 -
1(
#765
0(
#770
b10001 -
1(
#775
0(
#780
b10010 -
1(
#785
0(
#790
b10011 -
1(
#795
0(
#800
1&
0#
1%
0$
0+
b0 -
1(
#805
0(
#810
b1 -
1(
#815
0(
#820
b10 -
1(
b100 .
0*
#825
0(
#830
b11 -
1(
#835
0(
#840
b100 -
1(
#845
0(
#850
b101 -
1(
#855
0(
#860
b110 -
1(
#865
0(
#870
b111 -
1(
#875
0(
#880
b1000 -
1(
#885
0(
#890
b1001 -
1(
#895
0(
#900
b1010 -
1(
#905
0(
#910
b1011 -
1(
#915
0(
#920
b1100 -
1(
#925
0(
#930
b1101 -
1(
#935
0(
#940
b1110 -
1(
#945
0(
#950
b1111 -
1(
#955
0(
#960
b10000 -
1(
#965
0(
#970
b10001 -
1(
#975
0(
#980
b10010 -
1(
#985
0(
#990
b10011 -
1(
#995
0(
#1000
0&
1"
1,
b0 -
1(
#1005
0(
#1010
b1 -
1(
#1015
0(
#1020
b10 -
1(
b101 .
1*
#1025
0(
#1030
b11 -
1(
#1035
0(
#1040
b100 -
1(
#1045
0(
#1050
b101 -
1(
#1055
0(
#1060
b110 -
1(
#1065
0(
#1070
b111 -
1(
#1075
0(
#1080
b1000 -
1(
#1085
0(
#1090
b1001 -
1(
#1095
0(
#1100
b1010 -
1(
#1105
0(
#1110
b1011 -
1(
#1115
0(
#1120
b1100 -
1(
#1125
0(
#1130
b1101 -
1(
#1135
0(
#1140
b1110 -
1(
#1145
0(
#1150
b1111 -
1(
#1155
0(
#1160
b10000 -
1(
#1165
0(
#1170
b10001 -
1(
#1175
0(
#1180
b10010 -
1(
#1185
0(
#1190
b10011 -
1(
#1195
0(
#1200
0"
1'
0%
1$
1+
b0 -
1(
#1205
0(
#1210
b1 -
1(
#1215
0(
#1220
b10 -
1(
b110 .
0*
#1225
0(
#1230
b11 -
1(
#1235
0(
#1240
b100 -
1(
#1245
0(
#1250
b101 -
1(
#1255
0(
#1260
b110 -
1(
#1265
0(
#1270
b111 -
1(
#1275
0(
#1280
b1000 -
1(
#1285
0(
#1290
b1001 -
1(
#1295
0(
#1300
b1010 -
1(
#1305
0(
#1310
b1011 -
1(
#1315
0(
#1320
b1100 -
1(
#1325
0(
#1330
b1101 -
1(
#1335
0(
#1340
b1110 -
1(
#1345
0(
#1350
b1111 -
1(
#1355
0(
#1360
b10000 -
1(
#1365
0(
#1370
b10001 -
1(
#1375
0(
#1380
b10010 -
1(
#1385
0(
#1390
b10011 -
1(
#1395
0(
#1400
1#
0'
0,
b0 -
1(
#1405
0(
#1410
b1 -
1(
#1415
0(
#1420
b10 -
1(
b111 .
1*
#1425
0(
#1430
b11 -
1(
#1435
0(
#1440
b100 -
1(
#1445
0(
#1450
b101 -
1(
#1455
0(
#1460
b110 -
1(
#1465
0(
#1470
b111 -
1(
#1475
0(
#1480
b1000 -
1(
#1485
0(
#1490
b1001 -
1(
#1495
0(
#1500
b1010 -
1(
#1505
0(
#1510
b1011 -
1(
#1515
0(
#1520
b1100 -
1(
#1525
0(
#1530
b1101 -
1(
#1535
0(
#1540
b1110 -
1(
#1545
0(
#1550
b1111 -
1(
#1555
0(
#1560
b10000 -
1(
#1565
0(
#1570
b10001 -
1(
#1575
0(
#1580
b10010 -
1(
#1585
0(
#1590
b10011 -
1(
#1595
0(
#1600
1&
0#
1%
0$
0+
b0 -
1(
#1605
0(
#1610
b1 -
1(
#1615
0(
#1620
b10 -
1(
b1000 .
0*
#1625
0(
#1630
b11 -
1(
#1635
0(
#1640
b100 -
1(
#1645
0(
#1650
b101 -
1(
#1655
0(
#1660
b110 -
1(
#1665
0(
#1670
b111 -
1(
#1675
0(
#1680
b1000 -
1(
#1685
0(
#1690
b1001 -
1(
#1695
0(
#1700
b1010 -
1(
#1705
0(
#1710
b1011 -
1(
#1715
0(
#1720
b1100 -
1(
#1725
0(
#1730
b1101 -
1(
#1735
0(
#1740
b1110 -
1(
#1745
0(
#1750
b1111 -
1(
#1755
0(
#1760
b10000 -
1(
#1765
0(
#1770
b10001 -
1(
#1775
0(
#1780
b10010 -
1(
#1785
0(
#1790
b10011 -
1(
#1795
0(
#1800
0&
1"
1,
b0 -
1(
#1805
0(
#1810
b1 -
1(
#1815
0(
#1820
b10 -
1(
b1001 .
1*
#1825
0(
#1830
b11 -
1(
#1835
0(
#1840
b100 -
1(
#1845
0(
#1850
b101 -
1(
#1855
0(
#1860
b110 -
1(
#1865
0(
#1870
b111 -
1(
#1875
0(
#1880
b1000 -
1(
#1885
0(
#1890
b1001 -
1(
#1895
0(
#1900
b1010 -
1(
#1905
0(
#1910
b1011 -
1(
#1915
0(
#1920
b1100 -
1(
#1925
0(
#1930
b1101 -
1(
#1935
0(
#1940
b1110 -
1(
#1945
0(
#1950
b1111 -
1(
#1955
0(
#1960
b10000 -
1(
#1965
0(
#1970
b10001 -
1(
#1975
0(
#1980
b10010 -
1(
#1985
0(
#1990
b10011 -
1(
#1995
0(
#2000
0"
1'
0%
1$
1+
b0 -
1(
#2005
0(
#2010
b1 -
1(
#2015
0(
#2020
b10 -
1(
b1010 .
0*
#2025
0(
#2030
b11 -
1(
#2035
0(
#2040
b100 -
1(
#2045
0(
#2050
b101 -
1(
#2055
0(
#2060
b110 -
1(
#2065
0(
#2070
b111 -
1(
#2075
0(
#2080
b1000 -
1(
#2085
0(
#2090
b1001 -
1(
#2095
0(
#2100
b1010 -
1(
#2105
0(
#2110
b1011 -
1(
#2115
0(
#2120
b1100 -
1(
#2125
0(
#2130
b1101 -
1(
#2135
0(
#2140
b1110 -
1(
#2145
0(
#2150
b1111 -
1(
#2155
0(
#2160
b10000 -
1(
#2165
0(
#2170
b10001 -
1(
#2175
0(
#2180
b10010 -
1(
#2185
0(
#2190
b10011 -
1(
#2195
0(
#2200
1#
0'
0,
b0 -
1(
#2205
0(
#2210
b1 -
1(
#2215
0(
#2220
b10 -
1(
b1011 .
1*
